{"meta":{"name":"@walmart/wmreact-base","title":"Base","description":"Core non-interactive Hydra UI components","github":"https://gecgithub01.walmart.com/react/base/","version":"7.1.0"},"imports":[{"ref":"Body","path":"components/body"},{"ref":"Copy","path":"components/copy"},{"ref":"Descriptions","path":"components/descriptions"},{"ref":"Heading","path":"components/heading"},{"ref":"Icon","path":"components/icon"},{"ref":"Image","path":"components/image"},{"ref":"ImageLoader","path":"components/image-loader"},{"ref":"Link","path":"components/link"}],"components":[{"title":"Body","examples":[{"type":"playground","code":"<Body title=\"Test Title\">\n  <p>Body Copy!</p>\n</Body>","noRender":true}],"options":{"image":"./images/Body.png"}},{"title":"Copy","examples":[{"type":"playground","code":"<div>\n  <Copy>Base Copy</Copy>\n  <Copy.OpenLeading>Open Leading Copy</Copy.OpenLeading>\n  <Copy.Small>Small Copy</Copy.Small>\n  <Copy.Mini>Mini Copy</Copy.Mini>\n</div>\n","noRender":true}],"options":{"image":"./images/Copy.png"}},{"title":"Descriptions","examples":[{"type":"playground","code":"<Descriptions>\n  <Descriptions.Term>Term</Descriptions.Term>\n  <Descriptions.Description>Description</Descriptions.Description>\n</Descriptions>\n","noRender":true}],"options":{"image":"./images/Descriptions.png"}},{"title":"Heading","examples":[{"type":"playground","code":"<div>\n  <Heading.H1>H1</Heading.H1>\n  <Heading.H2>H2</Heading.H2>\n  <Heading.H3>H3</Heading.H3>\n  <Heading.H4>H4</Heading.H4>\n  <Heading.H5>H5</Heading.H5>\n  <Heading.H6>H6</Heading.H6>\n</div>\n","noRender":true}],"options":{"image":"./images/Heading.png"}},{"title":"Icon","examples":[{"type":"playground","code":"<div>\n  <Icon name=\"truck\" size={1}/>\n  <Icon name=\"list\" size={1}/>\n  <Icon name=\"pin\" size={1}/>\n  <Icon name=\"search\" size={1}/>\n  <Icon name=\"help\" size={1}/>\n  <Icon name=\"zoom\" size={1}/>\n  <Icon name=\"zoom-out\" size={1}/>\n  <Icon name=\"menu\" size={1}/>\n  <Icon name=\"grid\" size={1}/>\n  <Icon name=\"lock\" size={1}/>\n  <Icon name=\"package\" size={1}/>\n  <Icon name=\"print\" size={1}/>\n  <Icon name=\"mail\" size={1}/>\n  <Icon name=\"twitter\" size={1}/>\n  <Icon name=\"pinterest\" size={1}/>\n  <Icon name=\"facebook\" size={1}/>\n  <Icon name=\"youtube\" size={1}/>\n  <Icon name=\"google-plus\" size={1}/>\n  <Icon name=\"vudu\" size={1}/>\n  <Icon name=\"mobile\" size={1}/>\n  <Icon name=\"add-to-cart\" size={1}/>\n  <Icon name=\"add-to-list\" size={1}/>\n  <Icon name=\"store\" size={1}/>\n  <Icon name=\"add\" size={1}/>\n  <Icon name=\"weekly-ad\" size={1}/>\n  <Icon name=\"angle-left\" size={1}/>\n  <Icon name=\"angle-right\" size={1}/>\n  <Icon name=\"ok\" size={1}/>\n  <Icon name=\"exclamation-circle\" size={1}/>\n  <Icon name=\"caret-down\" size={1}/>\n  <Icon name=\"caret-up\" size={1}/>\n  <Icon name=\"remove\" size={1}/>\n  <Icon name=\"play\" size={1}/>\n  <Icon name=\"ban-circle\" size={1}/>\n  <Icon name=\"spark\" size={1}/>\n  <Icon name=\"trophy\" size={1}/>\n  <Icon name=\"star\" size={1}/>\n  <Icon name=\"user\" size={1}/>\n  <Icon name=\"thumbs-up\" size={1}/>\n  <Icon name=\"comment\" size={1}/>\n  <Icon name=\"play-circle\" size={1}/>\n  <Icon name=\"new-window\" size={1}/>\n  <Icon name=\"thumbs-alt-up\" size={1}/>\n  <Icon name=\"thumbs-alt-down\" size={1}/>\n  <Icon name=\"flag\" size={1}/>\n  <Icon name=\"modal\" size={1}/>\n  <Icon name=\"clock\" size={1}/>\n  <Icon name=\"savings-catcher\" size={1}/>\n  <Icon name=\"gift-card\" size={1}/>\n  <Icon name=\"credit-card\" size={1}/>\n  <Icon name=\"membership\" size={1}/>\n</div>","noRender":true}],"options":{"image":"./images/Icon.png"}},{"title":"Image","examples":[{"type":"playground","code":"<div>\n  <Image src=\"http://placehold.it/1000x1000\" size={30}/>\n  <Image src=\"http://placehold.it/1000x1000\" size={45}/>\n  <Image src=\"http://placehold.it/1000x1000\" size={50}/>\n  <Image src=\"http://placehold.it/1000x1000\" size={60}/>\n  <Image src=\"http://placehold.it/1000x1000\" size={100}/>\n  <Image src=\"http://placehold.it/1000x1000\" size={125}/>\n  <Image src=\"http://placehold.it/1000x1000\" size={150}/>\n  <Image src=\"http://placehold.it/1000x1000\" size={180}/>\n</div>","noRender":true}],"options":{"image":"./images/Image.png"}},{"title":"Link","examples":[{"type":"playground","code":"<div>\n  <Link href=\"#\">Base Link</Link>\n  <Link href=\"#\" arrow={true}>Arrow Link</Link>\n  <Link href=\"#\" active={true}>Active Link</Link>\n  <Link href=\"#\" dropdown={true}>Dropdown Link</Link>\n</div>","noRender":true}],"options":{"image":"./images/Link.png"}}]}