{"meta":{"name":"@walmart/wmreact-modal","description":"A generic modal component.","github":"https://gecgithub01.walmart.com/react/modal/","version":"0.0.2"},"imports":[{"path":"components/modal"},{"path":"components/layout"},{"path":"components/container"},{"path":"components/button-group"}],"components":[],"usage":["https://gecgithub01.walmart.com/R-Transaction/pac","https://gecgithub01.walmart.com/R-Transaction/cart-body","https://gecgithub01.walmart.com/R-Transaction/cart","https://gecgithub01.walmart.com/R-Transaction/checkout"]}