{"meta":{"name":"@walmart/wmreact-navigation","github":"https://gecgithub01.walmart.com/react/navigation/","version":"2.2.0"},"usage":["https://gecgithub01.walmart.com/R-CAT/topic","https://gecgithub01.walmart.com/R-Discovery/collections","https://gecgithub01.walmart.com/R-Discovery/non-config","https://gecgithub01.walmart.com/R-Discovery/product","https://gecgithub01.walmart.com/R-User/account","https://gecgithub01.walmart.com/R-sams-membership/Account","https://gecgithub01.walmart.com/R-sams-on-pangaea-ui/product","https://gecgithub01.walmart.com/R-search-category/search-electrode-app","https://gecgithub01.walmart.com/electrode/electrode-showcase","https://gecgithub01.walmart.com/react-category/tempo-modules","https://gecgithub01.walmart.com/react/category-components","https://gecgithub01.walmart.com/react/flux-example","https://gecgithub01.walmart.com/react/showcase-thor"]}